pylint_absolute_imports/__init__.py
pylint_absolute_imports/checker.py
pylint_absolute_imports-1.1.0.dist-info/LICENSE
pylint_absolute_imports-1.1.0.dist-info/METADATA
pylint_absolute_imports-1.1.0.dist-info/WHEEL
pylint_absolute_imports-1.1.0.dist-info/top_level.txt
pylint_absolute_imports-1.1.0.dist-info/RECORD
